[
  {
    "name": "Alexander",
    "ingredients": [
      {
        "name": "Cognac",
        "amount": 30,
        "unit": "ml"
      },
      {
        "name": "Creme de Cacao",
        "amount": 30,
        "unit": "ml"
      },
      {
        "name": "Fresh Cream",
        "amount": 30,
        "unit": "ml"
      }
    ],
    "garnish": "Sprinkle fresh ground nutmeg on top.",
    "method": "Pour all ingredients into cocktail shaker filled with ice cubes. Shake and strain into a chilled cocktail glass.",
    "source": "The Unforgettables"
  },
  {
    "name": "Americano",
    "ingredients": [
      {
        "name": "Campari",
        "amount": 30,
        "unit": "ml"
      },
      {
        "name": "Sweet Vermouth",
        "amount": 30,
        "unit": "ml"
      },
      {
        "name": "Soda Water",
        "amount": null,
        "unit": "A splash of"
      }
    ],
    "garnish": "Garnish with half orange slice and a lemon zest.",
    "method": "Mix the ingredients directly in an old fashioned glass filled with ice cubes. Add a splash of Soda Water. Stir gently.",
    "source": "The Unforgettables"
  },
  {
    "name": "Angel Face",
    "ingredients": [
      {
        "name": "Gin",
        "amount": 30,
        "unit": "ml"
      },
      {
        "name": "Apricot Brandy",
        "amount": 30,
        "unit": "ml"
      },
      {
        "name": "Calvados",
        "amount": 30,
        "unit": "ml"
      }
    ],
    "garnish": null,
    "method": "Pour all ingredients into cocktail shaker filled with ice cubes. Shake and strain into a chilled cocktail glass.",
    "source": "The Unforgettables"
  },
  {
    "name": "Aviation",
    "ingredients": [
      {
        "name": "Gin",
        "amount": 45,
        "unit": "ml"
      },
      {
        "name": "Maraschino Liqueur",
        "amount": 15,
        "unit": "ml"
      },
      {
        "name": "Lemon Juice",
        "amount": 15,
        "unit": "ml"
      },
      {
        "name": "Creme de Violette",
        "amount": 1,
        "unit": "barspoon"
      }
    ],
    "garnish": "Optional Maraschino cherry",
    "method": "Add all ingredients into a cocktail shaker. Shake with cracked ice and strain into a chilled cocktail glass.",
    "source": "The Unforgettables"
  },
  {
    "name": "Between the Sheets",
    "ingredients": [
      {
        "name": "White Rum",
        "amount": 30,
        "unit": "ml"
      },
      {
        "name": "Cognac",
        "amount": 30,
        "unit": "ml"
      },
      {
        "name": "Triple Sec",
        "amount": 30,
        "unit": "ml"
      },
      {
        "name": "Lemon Juice",
        "amount": 20,
        "unit": "ml"
      }
    ],
    "garnish": null,
    "method": "Add all ingredients into a cocktail shaker. Shake with ice and strain into a chilled cocktail glass.",
    "source": "The Unforgettables"
  },
  {
    "name": "Boulevardier",
    "ingredients": [
      {
        "name": "Bourbon",
        "amount": 45,
        "unit": "ml"
      },
      {
        "name": "Campari",
        "amount": 30,
        "unit": "ml"
      },
      {
        "name": "Sweet Vermouth",
        "amount": 30,
        "unit": "ml"
      }
    ],
    "garnish": "Garnish with a orange zest, optionally a lemon zest.",
    "method": "Pour all ingredients into mixing glass with ice cubes. Stir well. Strain into chilled cocktail glass.",
    "source": "The Unforgettables"
  },
  {
    "name": "Brandy Crusta",
    "ingredients": [
      {
        "name": "Brandy",
        "amount": 52.5,
        "unit": "ml"
      },
      {
        "name": "Maraschino Liqueur",
        "amount": 7.5,
        "unit": "ml"
      },
      {
        "name": "Curacao",
        "amount": 1,
        "unit": "barspoon"
      },
      {
        "name": "Lemon Juice",
        "amount": 15,
        "unit": "ml"
      },
      {
        "name": "Simple Syrup",
        "amount": 1,
        "unit": "barspoon"
      },
      {
        "name": "Angostura Bitters",
        "amount": 2,
        "unit": "dashes"
      }
    ],
    "garnish": "Rub a slice of orange (or lemon) around the rim of the glass and dip it in pulverized white sugar, so that the sugar will adhere to the edge of the glass. Carefully curling place the orange/lemon peel around the inside of the glass.",
    "method": "Mix together all ingredients with ice cubes in a mixing glass and strain into prepared slim cocktail glass.",
    "source": "The Unforgettables"
  },
  {
    "name": "Casino",
    "ingredients": [
      {
        "name": "Old Tom Gin",
        "amount": 40,
        "unit": "ml"
      },
      {
        "name": "Maraschino Liqueur",
        "amount": 10,
        "unit": "ml"
      },
      {
        "name": "Lemon Juice",
        "amount": 10,
        "unit": "ml"
      },
      {
        "name": "Orange Bitters",
        "amount": 2,
        "unit": "dashes"
      }
    ],
    "garnish": "Garnish with a lemon zest and a maraschino cherry.",
    "method": "Pour all ingredients into cocktails shaker, shake well with ice, strain into chilled rocks glass with ice.",
    "source": "The Unforgettables"
  },
  {
    "name": "Clover Club",
    "ingredients": [
      {
        "name": "Gin",
        "amount": 45,
        "unit": "ml"
      },
      {
        "name": "Raspberry Syrup",
        "amount": 15,
        "unit": "ml"
      },
      {
        "name": "Lemon Juice",
        "amount": 15,
        "unit": "ml"
      },
      {
        "name": "Egg White",
        "amount": null,
        "unit": "A few drops of"
      }
    ],
    "garnish": "Fresh raspberries.",
    "method": "Pour all ingredients into cocktails shaker, shake well with ice, strain into chilled cocktail glass.",
    "source": "The Unforgettables"
  },
  {
    "name": "Daiquiri",
    "ingredients": [
      {
        "name": "White Rum",
        "amount": 60,
        "unit": "ml"
      },
      {
        "name": "Sugar",
        "amount": 2,
        "unit": "barspoons"
      },
      {
        "name": "Lime Juice",
        "amount": 20,
        "unit": "ml"
      }
    ],
    "garnish": null,
    "method": "In a cocktail shaker add all ingredients. Stir well to dissolve the sugar. Add ice and shake. Strain into chilled cocktail glass.",
    "source": "The Unforgettables"
  },
  {
    "name": "Dry Martini",
    "ingredients": [
      {
        "name": "Gin",
        "amount": 60,
        "unit": "ml"
      },
      {
        "name": "Dry Vermouth",
        "amount": 10,
        "unit": "ml"
      }
    ],
    "garnish": "Squeeze oil from lemon peel onto the drink, or garnish with a green olives if requested.",
    "method": "Pour all ingredients into mixing glass with ice cubes. Stir well. Strain into chilled martini cocktail glass.",
    "source": "The Unforgettables"
  },
  {
    "name": "Gin Fizz",
    "ingredients": [
      {
        "name": "Gin",
        "amount": 45,
        "unit": "ml"
      },
      {
        "name": "Lemon Juice",
        "amount": 30,
        "unit": "ml"
      },
      {
        "name": "Simple Syrup",
        "amount": 10,
        "unit": "ml"
      },
      {
        "name": "Soda Water",
        "amount": null,
        "unit": "A splash of"
      }
    ],
    "garnish": "Garnish with lemon slice, optional lemon zest.",
    "method": "Shake all ingredients with ice except soda water. Pour into thin tall Tumbler glass without ice, top with a splash soda water.",
    "source": "The Unforgettables"
  },
  {
    "name": "Hanky Panky",
    "ingredients": [
      {
        "name": "London Dry Gin",
        "amount": 45,
        "unit": "ml"
      },
      {
        "name": "Sweet Vermouth",
        "amount": 45,
        "unit": "ml"
      },
      {
        "name": "Fernet Branca",
        "amount": 7.5,
        "unit": "ml"
      }
    ],
    "garnish": "Orange Zest.",
    "method": "Pour all ingredients into mixing glass with ice cubes. Stir well. Strain into chilled cocktail glass.",
    "source": "The Unforgettables"
  },
  {
    "name": "John Collins",
    "ingredients": [
      {
        "name": "Gin",
        "amount": 45,
        "unit": "ml"
      },
      {
        "name": "Lemon Juice",
        "amount": 30,
        "unit": "ml"
      },
      {
        "name": "Simple Syrup",
        "amount": 15,
        "unit": "ml"
      },
      {
        "name": "Soda Water",
        "amount": 60,
        "unit": "ml"
      }
    ],
    "garnish": "Garnish with lemon slice and maraschino cherry.",
    "method": "Pour all ingredients directly into highball filled with ice. Stir gently.",
    "note": "Use ‘Old Tom’ Gin for the Tom Collins cocktail.",
    "source": "The Unforgettables"
  },
  {
    "name": "Last Word",
    "ingredients": [
      {
        "name": "Gin",
        "amount": 22.5,
        "unit": "ml"
      },
      {
        "name": "Green Chartreuse",
        "amount": 22.5,
        "unit": "ml"
      },
      {
        "name": "Maraschino Liqueur",
        "amount": 22.5,
        "unit": "ml"
      },
      {
        "name": "Lime Juice",
        "amount": 22.5,
        "unit": "ml"
      }
    ],
    "garnish": null,
    "method": "Add all ingredients into a cocktail shaker. Shake with ice and strain into a chilled cocktail glass.",
    "note": null,
    "source": "The Unforgettables"
  },
  {
    "name": "Manhattan",
    "ingredients": [
      {
        "name": "Rye Whiskey",
        "amount": 50,
        "unit": "ml"
      },
      {
        "name": "Sweet Vermouth",
        "amount": 20,
        "unit": "ml"
      },
      {
        "name": "Angostura Bitters",
        "amount": 1,
        "unit": "dash"
      }
    ],
    "garnish": "Garnish with cocktail cherry.",
    "method": "Pour all ingredients into mixing glass with ice cubes. Stir well. Strain into chilled cocktail glass.",
    "note": null,
    "source": "The Unforgettables"
  },
  {
    "name": "Martinez",
    "ingredients": [
      {
        "name": "London Dry Gin",
        "amount": 45,
        "unit": "ml"
      },
      {
        "name": "Sweet Vermouth",
        "amount": 45,
        "unit": "ml"
      },
      {
        "name": "Maraschino Liqueur",
        "amount": 1,
        "unit": "barspoon"
      },
      {
        "name": "Orange Bitters",
        "amount": 2,
        "unit": "dashes"
      }
    ],
    "garnish": "Lemon zest.",
    "method": "Pour all ingredients into mixing glass with ice cubes. Stir well. Strain into chilled cocktail glass.",
    "note": null,
    "source": "The Unforgettables"
  },
  {
    "name": "Mary Pickford",
    "ingredients": [
      {
        "name": "White Rum",
        "amount": 45,
        "unit": "ml"
      },
      {
        "name": "Pineapple Juice",
        "amount": 45,
        "unit": "ml"
      },
      {
        "name": "Maraschino Liqueur",
        "amount": 7.5,
        "unit": "ml"
      },
      {
        "name": "Grenadine",
        "amount": 5,
        "unit": "ml"
      }
    ],
    "garnish": null,
    "method": "Pour all ingredients into cocktail shaker, shake well with ice, strain into chilled cocktail glass.",
    "note": null,
    "source": "The Unforgettables"
  },
  {
    "name": "Monkey Gland",
    "ingredients": [
      {
        "name": "Dry Gin",
        "amount": 45,
        "unit": "ml"
      },
      {
        "name": "Orange Juice",
        "amount": 45,
        "unit": "ml"
      },
      {
        "name": "Absinthe",
        "amount": 1,
        "unit": "tbsp"
      },
      {
        "name": "Grenadine",
        "amount": 1,
        "unit": "tbsp"
      }
    ],
    "garnish": null,
    "method": "Pour all ingredients into cocktail shaker, shake well with ice, strain into chilled cocktail glass.",
    "note": null,
    "source": "The Unforgettables"
  },
  {
    "name": "Negroni",
    "ingredients": [
      {
        "name": "Gin",
        "amount": 30,
        "unit": "ml"
      },
      {
        "name": "Campari",
        "amount": 30,
        "unit": "ml"
      },
      {
        "name": "Sweet Vermouth",
        "amount": 30,
        "unit": "ml"
      }
    ],
    "garnish": "Garnish with half orange slice.",
    "method": "Pour all ingredients directly into chilled old fashioned glass filled with ice , Stir gently.",
    "note": null,
    "source": "The Unforgettables"
  },
  {
    "name": "Old Fashioned",
    "ingredients": [
      {
        "name": "Bourbon",
        "amount": 45,
        "unit": "ml"
      },
      {
        "name": "Sugar",
        "amount": 1,
        "unit": "cube"
      },
      {
        "name": "Angostura Bitters",
        "amount": null,
        "unit": "a few dashes"
      },
      {
        "name": "Water",
        "amount": null,
        "unit": "a few dashes"
      }
    ],
    "garnish": "Garnish with orange slice or zest, and a cocktail cherry.",
    "method": "Place sugar cube in old fashioned glass and saturate with bitter, add few dashes of plain water. Muddle until dissolved. Fill the glass with ice cubes and add whiskey. Stir gently.",
    "note": null,
    "source": "The Unforgettables"
  },
  {
    "name": "Paradise",
    "ingredients": [
      {
        "name": "Gin",
        "amount": 30,
        "unit": "ml"
      },
      {
        "name": "Apricot Brandy",
        "amount": 20,
        "unit": "ml"
      },
      {
        "name": "Orange Juice",
        "amount": 15,
        "unit": "ml"
      }
    ],
    "garnish": null,
    "method": "Pour all ingredients into cocktail shaker, shake well with ice, strain into chilled cocktail glass.",
    "note": null,
    "source": "The Unforgettables"
  },
  {
    "name": "Planter's Punch",
    "ingredients": [
      {
        "name": "Jamaican Rum",
        "amount": 45,
        "unit": "ml"
      },
      {
        "name": "Lime Juice",
        "amount": 15,
        "unit": "ml"
      },
      {
        "name": "Sugar Cane Juice",
        "amount": 30,
        "unit": "ml"
      }
    ],
    "garnish": "Garnish with orange zest.",
    "method": "Pour all ingredients directly in a small tumbler or a typical terracotta glass.",
    "note": "Add dilution up to taste, it can be given by water, ice or fresh juices.",
    "source": "The Unforgettables"
  },
  {
    "name": "Porto Flip",
    "ingredients": [
      {
        "name": "Brandy",
        "amount": 15,
        "unit": "ml"
      },
      {
        "name": "Red Tawny Port",
        "amount": 45,
        "unit": "ml"
      },
      {
        "name": "Egg Yolk",
        "amount": 10,
        "unit": "ml"
      }
    ],
    "garnish": "Sprinkle with fresh ground nutmeg.",
    "method": "Pour all ingredients into cocktail shaker, shake well with ice, strain into chilled cocktail glass.",
    "note": null,
    "source": "The Unforgettables"
  },
  {
    "name": "Ramos Fizz",
    "ingredients": [
      {
        "name": "Gin",
        "amount": 45,
        "unit": "ml"
      },
      {
        "name": "Lime Juice",
        "amount": 15,
        "unit": "ml"
      },
      {
        "name": "Lemon Juice",
        "amount": 15,
        "unit": "ml"
      },
      {
        "name": "Simple Syrup",
        "amount": 30,
        "unit": "ml"
      },
      {
        "name": "Egg White",
        "amount": 30,
        "unit": "ml"
      },
      {
        "name": "Orange Flower Water",
        "amount": 3,
        "unit": "dashes"
      },
      {
        "name": "Vanilla Extract",
        "amount": 2,
        "unit": "drops"
      },
      {
        "name": "Soda Water",
        "amount": null,
        "unit": "to top"
      }
    ],
    "garnish": null,
    "method": "Pour all ingredients except soda water in a cocktail shaker with ice, Shake for two minutes, double strain in a glass, pour the drink back in the shaker and hard shake without ice for one minute. Strain into a highball glass, top up with soda.",
    "note": "The drink was invented by Henry Ramos in 1888, at his bar Meyer’s Table d'Hotel Internationale in New Orleans. The Ramos Fizz was originally shaken for 12 minutes by a crew of 30 bartenders who passed the shaker from one to another.",
    "source": "The Unforgettables"
  },
  {
    "name": "Rusty Nail",
    "ingredients": [
      {
        "name": "Scotch Whisky",
        "amount": 45,
        "unit": "ml"
      },
      {
        "name": "Drambuie",
        "amount": 25,
        "unit": "ml"
      }
    ],
    "garnish": "Garnish with lemon zest.",
    "method": "Pour all ingredients directly into an old fashioned glass filled with ice. Stir gently.",
    "note": null,
    "source": "The Unforgettables"
  },
  {
    "name": "Sazerac",
    "ingredients": [
      {
        "name": "Cognac",
        "amount": 50,
        "unit": "ml"
      },
      {
        "name": "Absinthe",
        "amount": 10,
        "unit": "ml"
      },
      {
        "name": "Sugar",
        "amount": 1,
        "unit": "cube"
      },
      {
        "name": "Peychaud's Bitters",
        "amount": 2,
        "unit": "dashes"
      }
    ],
    "garnish": "Garnish with lemon zest.",
    "method": "Rinse a chilled old-fashioned glass with the absinthe, add crushed ice and set it aside. Stir the remaining ingredients over ice in a mixing glass . Discard the ice and any excess absinthe from the prepared glass, strain the mixed drink into the glass.",
    "note": "The original recipe changed after the American Civil War, Rye Whiskey substituted Cognac as it became hard to obtain.",
    "source": "The Unforgettables"
  },
  {
    "name": "Sidecar",
    "ingredients": [
      {
        "name": "Cognac",
        "amount": 50,
        "unit": "ml"
      },
      {
        "name": "Triple Sec",
        "amount": 20,
        "unit": "ml"
      },
      {
        "name": "Lemon Juice",
        "amount": 20,
        "unit": "ml"
      }
    ],
    "garnish": null,
    "method": "Pour all ingredients into cocktail shaker, shake well with ice, strain into a chilled cocktail glass.",
    "note": null,
    "source": "The Unforgettables"
  },
  {
    "name": "Stinger",
    "ingredients": [
      {
        "name": "Cognac",
        "amount": 50,
        "unit": "ml"
      },
      {
        "name": "White Creme de Menthe",
        "amount": 20,
        "unit": "ml"
      }
    ],
    "garnish": "Optional mint leave.",
    "method": "Pour all ingredients into mixing glass with ice cubes. Stir well. Strain into chilled martini cocktail glass.",
    "note": null,
    "source": "The Unforgettables"
  },
  {
    "name": "Tuxedo",
    "ingredients": [
      {
        "name": "Old Tom Gin",
        "amount": 30,
        "unit": "ml"
      },
      {
        "name": "Dry Vermouth",
        "amount": 30,
        "unit": "ml"
      },
      {
        "name": "Maraschino Liqueur",
        "amount": 0.5,
        "unit": "barspoon"
      },
      {
        "name": "Absinthe",
        "amount": 0.25,
        "unit": "barspoon"
      },
      {
        "name": "Orange Bitters",
        "amount": 3,
        "unit": "dashes"
      }
    ],
    "garnish": "Garnish with cherry and lemon zest",
    "method": "Pour all ingredients into mixing glass with ice cubes. Stir well. Strain into chilled martini cocktail glass.",
    "note": null,
    "source": "The Unforgettables"
  },
  {
    "name": "Vieux Carre",
    "ingredients": [
      {
        "name": "Rye Whiskey",
        "amount": 30,
        "unit": "ml"
      },
      {
        "name": "Cognac",
        "amount": 30,
        "unit": "ml"
      },
      {
        "name": "Sweet Vermouth",
        "amount": 30,
        "unit": "ml"
      },
      {
        "name": "Benedictine",
        "amount": 1,
        "unit": "barspoon"
      },
      {
        "name": "Peychaud's Bitters",
        "amount": 2,
        "unit": "dashes"
      }
    ],
    "garnish": "Garnish with orange zest and maraschino cherry.",
    "method": "Pour all ingredients into mixing glass with ice cubes. Stir well. Strain into chilled cocktail glass.",
    "note": null,
    "source": "The Unforgettables"
  },
  {
    "name": "Whiskey Sour",
    "ingredients": [
      {
        "name": "Bourbon",
        "amount": 45,
        "unit": "ml"
      },
      {
        "name": "Lemon Juice",
        "amount": 25,
        "unit": "ml"
      },
      {
        "name": "Simple Syrup",
        "amount": 20,
        "unit": "ml"
      },
      {
        "name": "Egg White",
        "amount": 20,
        "unit": "ml"
      }
    ],
    "garnish": "Garnish with half orange slice and maraschino cherry, optionally use orange zest.",
    "method": "Pour all ingredients into cocktail shaker filled with ice. Shake well. Strain into cobbler glass. If served “On the rocks”, strain ingredients into old fashioned glass filled with ice.",
    "note": "If egg white is used shake little harder to release and incorporate the foam from the egg white.",
    "source": "The Unforgettables"
  },
  {
    "name": "White Lady",
    "ingredients": [
      {
        "name": "Gin",
        "amount": 40,
        "unit": "ml"
      },
      {
        "name": "Lemon Juice",
        "amount": 20,
        "unit": "ml"
      },
      {
        "name": "Triple Sec",
        "amount": 30,
        "unit": "ml"
      }
    ],
    "garnish": null,
    "method": "Pour all ingredients into cocktail shaker, shake well with ice, strain into chilled cocktail glass.",
    "note": null,
    "source": "The Unforgettables"
  },
  {
    "name": "Bellini",
    "ingredients": [
      {
        "name": "Prosecco",
        "amount": 100,
        "unit": "ml"
      },
      {
        "name": "White Peach Puree",
        "amount": 50,
        "unit": "ml"
      }
    ],
    "garnish": null,
    "method": "Pour peach puree into the mixing glass with ice, add the Prosecco. Stir gently and pour in a chilled flute glass.",
    "note": "PUCCINI – Fresh Mandarin Orange Juice;\nROSSINI – Fresh Strawberry Puree;\nTINTORETTO – Fresh Pomegranate Juice.",
    "source": "Contemporary Classics"
  },
  {
    "name": "Black Russian",
    "ingredients": [
      {
        "name": "Vodka",
        "amount": 50,
        "unit": "ml"
      },
      {
        "name": "Coffee Liqueur",
        "amount": 20,
        "unit": "ml"
      }
    ],
    "garnish": null,
    "method": "Pour the ingredients into the old fashioned glass filled with ice cubes. Stir gently.",
    "note": "WHITE RUSSIAN – Float cream on the top and stir in slowly.",
    "source": "Contemporary Classics"
  },
  {
    "name": "Bloody Mary",
    "ingredients": [
      {
        "name": "Vodka",
        "amount": 45,
        "unit": "ml"
      },
      {
        "name": "Tomato Juice",
        "amount": 90,
        "unit": "ml"
      },
      {
        "name": "Lemon Juice",
        "amount": 15,
        "unit": "ml"
      },
      {
        "name": "Worcestershire Sauce",
        "amount": 2,
        "unit": "dashes"
      },
      {
        "name": "Tabasco",
        "amount": null,
        "unit": "to taste"
      },
      {
        "name": "Celery Salt",
        "amount": null,
        "unit": "to taste"
      },
      {
        "name": "Pepper",
        "amount": null,
        "unit": "to taste"
      }
    ],
    "garnish": "Celery, Lemon Wedge (Optional)",
    "method": "Stir gently all the ingredients in a mixing glass with ice, pour into rocks glass.",
    "note": "If requested served with ice, pour into highball glass.",
    "source": "Contemporary Classics"
  },
  {
    "name": "Caiprinha",
    "ingredients": [
      {
        "name": "Cachaca",
        "amount": 60,
        "unit": "ml"
      },
      {
        "name": "Lime Wedges",
        "amount": 6,
        "unit": "wedges"
      },
      {
        "name": "Sugar",
        "amount": 4,
        "unit": "tsp"
      }
    ],
    "garnish": null,
    "method": "Place lime and sugar into a double old fashioned glass and muddle gently. Fill the glass with cracked ice and add Cachaca. Stir gently to involve ingredients.",
    "note": "CAIPIROSKA – Instead of Cachaca use Vodka;\nCAIPIRISSIMA – Instead of Cachaca use Rum.",
    "source": "Contemporary Classics"
  },
  {
    "name": "Champagne Cocktail",
    "ingredients": [
      {
        "name": "Champagne",
        "amount": 90,
        "unit": "ml"
      },
      {
        "name": "Cognac",
        "amount": 10,
        "unit": "ml"
      },
      {
        "name": "Angostura Bitters",
        "amount": 2,
        "unit": "dashes"
      },
      {
        "name": "Grand Marnier",
        "amount": null,
        "unit": "a few drops of"
      },
      {
        "name": "Sugar",
        "amount": 1,
        "unit": "cube"
      }
    ],
    "garnish": "Garnish with orange zest and maraschino cherry.",
    "method": "Place the sugar cube with 2 dashes of bitters in a large Champagne glass, add the cognac. Pour gently chilled Champagne.",
    "note": null,
    "source": "Contemporary Classics"
  },
  {
    "name": "Corpse Reviver #2",
    "ingredients": [
      {
        "name": "Gin",
        "amount": 30,
        "unit": "ml"
      },
      {
        "name": "Cointreau",
        "amount": 30,
        "unit": "ml"
      },
      {
        "name": "Lillet Blanc",
        "amount": 30,
        "unit": "ml"
      },
      {
        "name": "Lemon Juice",
        "amount": 30,
        "unit": "ml"
      },
      {
        "name": "Absinthe",
        "amount": 1,
        "unit": "dash"
      }
    ],
    "garnish": "Garnish with orange zest.",
    "method": "Pour all ingredients into shaker with ice. Shake well and strain in chilled cocktail glass.",
    "note": null,
    "source": "Contemporary Classics"
  },
  {
    "name": "Cosmopolitan",
    "ingredients": [
      {
        "name": "Vodka Citron",
        "amount": 40,
        "unit": "ml"
      },
      {
        "name": "Cointreau",
        "amount": 15,
        "unit": "ml"
      },
      {
        "name": "Lime Juice",
        "amount": 15,
        "unit": "ml"
      },
      {
        "name": "Cranberry Juice",
        "amount": 30,
        "unit": "ml"
      }
    ],
    "garnish": "Garnish with lemon twist.",
    "method": "Add all ingredients into cocktail shaker filled with ice. Shake well and strain into large cocktail glass.",
    "note": null,
    "source": "Contemporary Classics"
  },
  {
    "name": "Cuba Libre",
    "ingredients": [
      {
        "name": "White Rum",
        "amount": 50,
        "unit": "ml"
      },
      {
        "name": "Cola",
        "amount": 120,
        "unit": "ml"
      },
      {
        "name": "Lime Juice",
        "amount": 10,
        "unit": "ml"
      }
    ],
    "garnish": "Garnish with lime wedge.",
    "method": "Build all ingredients in a highball glass filled with ice.",
    "note": null,
    "source": "Contemporary Classics"
  },
  {
    "name": "French 75",
    "ingredients": [
      {
        "name": "Gin",
        "amount": 30,
        "unit": "ml"
      },
      {
        "name": "Lemon Juice",
        "amount": 15,
        "unit": "ml"
      },
      {
        "name": "Simple Syrup",
        "amount": 15,
        "unit": "ml"
      },
      {
        "name": "Champagne",
        "amount": 60,
        "unit": "ml"
      }
    ],
    "garnish": null,
    "method": "Pour all the ingredients, except Champagne, into a shaker. Shake well and strain into a Champagne flute. Top up with Champagne. Stir gently.",
    "note": null,
    "source": "Contemporary Classics"
  },
  {
    "name": "French Connection",
    "ingredients": [
      {
        "name": "Cognac",
        "amount": 35,
        "unit": "ml"
      },
      {
        "name": "Amaretto",
        "amount": 35,
        "unit": "ml"
      }
    ],
    "garnish": null,
    "method": "Pour all ingredients directly into old fashioned glass filled with ice cubes. Stir gently.",
    "note": null,
    "source": "Contemporary Classics"
  },
  {
    "name": "Golden Dream",
    "ingredients": [
      {
        "name": "Galliano",
        "amount": 20,
        "unit": "ml"
      },
      {
        "name": "Triple Sec",
        "amount": 20,
        "unit": "ml"
      },
      {
        "name": "Orange Juice",
        "amount": 20,
        "unit": "ml"
      },
      {
        "name": "Cream",
        "amount": 10,
        "unit": "ml"
      }
    ],
    "garnish": null,
    "method": "Pour all ingredients into shaker filled with ice. Shake briskly for few seconds. Strain into chilled cocktail glass.",
    "note": null,
    "source": "Contemporary Classics"
  },
  {
    "name": "Grasshopper",
    "ingredients": [
      {
        "name": "White Creme de Cacao",
        "amount": 20,
        "unit": "ml"
      },
      {
        "name": "Green Creme de Menthe",
        "amount": 20,
        "unit": "ml"
      },
      {
        "name": "Cream",
        "amount": 20,
        "unit": "ml"
      }
    ],
    "garnish": "Optional mint leave.",
    "method": "Pour all ingredients into shaker filled with ice.\nShake briskly for few seconds. Strain into chilled cocktail glass.",
    "note": null,
    "source": "Contemporary Classics"
  },
  {
    "name": "Hemingway Special",
    "ingredients": [
      {
        "name": "White Rum",
        "amount": 60,
        "unit": "ml"
      },
      {
        "name": "Grapefruit Juice",
        "amount": 40,
        "unit": "ml"
      },
      {
        "name": "Maraschino Liqueur",
        "amount": 15,
        "unit": "ml"
      },
      {
        "name": "Lime Juice",
        "amount": 15,
        "unit": "ml"
      }
    ],
    "garnish": null,
    "method": "Pour all ingredients into a shaker with ice. Shake well and strain into a large cocktail glass.",
    "note": null,
    "source": "Contemporary Classics"
  },
  {
    "name": "Horse's Neck",
    "ingredients": [
      {
        "name": "Cognac",
        "amount": 40,
        "unit": "ml"
      },
      {
        "name": "Ginger Ale",
        "amount": 120,
        "unit": "ml"
      },
      {
        "name": "Angostura Bitters",
        "amount": 1,
        "unit": "dash"
      }
    ],
    "garnish": "Garnish with rind of one lemon spiral.",
    "method": "Pour Cognac and ginger ale directly into highball glass with ice cubes. Stir gently.\nIf preferred, add dashes of Angostura Bitter.",
    "note": null,
    "source": "Contemporary Classics"
  },
  {
    "name": "Irish Coffee",
    "ingredients": [
      {
        "name": "Irish Whiskey",
        "amount": 50,
        "unit": "ml"
      },
      {
        "name": "Coffee",
        "amount": 120,
        "unit": "ml"
      },
      {
        "name": "Cream",
        "amount": 50,
        "unit": "ml"
      },
      {
        "name": "Sugar",
        "amount": 1,
        "unit": "tsp"
      }
    ],
    "garnish": null,
    "method": "Warm black coffee is poured into a pre-heated Irish coffee glass. Whiskey and at least one teaspoon of sugar is added and stirred until dissolved. Fresh thick chilled cream is carefully poured over the back of a spoon held just above the surface of the coffee. The layer of cream will float on the coffee without mixing.\nPlain sugar can be replaced with sugar syrup",
    "note": null,
    "source": "Contemporary Classics"
  },
  {
    "name": "Kir",
    "ingredients": [
      {
        "name": "Dry White Wine",
        "amount": 90,
        "unit": "ml"
      },
      {
        "name": "Creme de cassis",
        "amount": 10,
        "unit": "ml"
      }
    ],
    "garnish": null,
    "method": "Pour Crème de Cassis into glass, top up with white wine.",
    "note": "KIR ROYAL – Use Champagne instead of white wine",
    "source": "Contemporary Classics"
  },
  {
    "name": "Long Island Iced Tea",
    "ingredients": [
      {
        "name": "Vodka",
        "amount": 15,
        "unit": "ml"
      },
      {
        "name": "Tequila",
        "amount": 15,
        "unit": "ml"
      },
      {
        "name": "White Rum",
        "amount": 15,
        "unit": "ml"
      },
      {
        "name": "Gin",
        "amount": 15,
        "unit": "ml"
      },
      {
        "name": "Cointreau",
        "amount": 15,
        "unit": "ml"
      },
      {
        "name": "Lemon Juice",
        "amount": 25,
        "unit": "ml"
      },
      {
        "name": "Simple Syrup",
        "amount": 30,
        "unit": "ml"
      },
      {
        "name": "Cola",
        "amount": null,
        "unit": "to top"
      }
    ],
    "garnish": "Lemon Slice (Optional)",
    "method": "Add all ingredients into highball glass filled with ice.\nStir gently.",
    "note": null,
    "source": "Contemporary Classics"
  },
  {
    "name": "Mai-Tai",
    "ingredients": [
      {
        "name": "Amber Jamaican Rum",
        "amount": 30,
        "unit": "ml"
      },
      {
        "name": "Martinique Molasses Rhum",
        "amount": 30,
        "unit": "ml"
      },
      {
        "name": "Orange Curacao",
        "amount": 15,
        "unit": "ml"
      },
      {
        "name": "Orgeat Syrup",
        "amount": 15,
        "unit": "ml"
      },
      {
        "name": "Lime Juice",
        "amount": 30,
        "unit": "ml"
      },
      {
        "name": "Simple Syrup",
        "amount": 7.5,
        "unit": "ml"
      }
    ],
    "garnish": "Garnish with pineapple spear, mint leaves and lime peel.",
    "method": "Add all ingredients into a shaker with ice. Shake and pour into a double rocks glass or an highball glass.",
    "note": "The Martinique molasses rum used by Trader Vic was not an Agricole rum but a type of rum from molasses.",
    "source": "Contemporary Classics"
  },
  {
    "name": "Margarita",
    "ingredients": [
      {
        "name": "Tequila Blanco",
        "amount": 50,
        "unit": "ml"
      },
      {
        "name": "Triple Sec",
        "amount": 20,
        "unit": "ml"
      },
      {
        "name": "Lime Juice",
        "amount": 15,
        "unit": "ml"
      }
    ],
    "garnish": "Half salt rim (Optional)",
    "method": "Add all ingredients into a shaker with ice.\nShake and strain into a chilled cocktail glass",
    "note": null,
    "source": "Contemporary Classics"
  },
  {
    "name": "Mimosa",
    "ingredients": [
      {
        "name": "Orange Juice",
        "amount": 75,
        "unit": "ml"
      },
      {
        "name": "Prosecco",
        "amount": 75,
        "unit": "ml"
      }
    ],
    "garnish": "Garnish with orange twist (optional).",
    "method": "Pour orange juice into flute glass and gently pour the sparkling wine. Stir gently.",
    "note": "Also known as Buck’s Fizz.",
    "source": "Contemporary Classics"
  },
  {
    "name": "Mint Julep",
    "ingredients": [
      {
        "name": "Bourbon",
        "amount": 60,
        "unit": "ml"
      },
      {
        "name": "Mint",
        "amount": 4,
        "unit": "sprigs"
      },
      {
        "name": "Powdered Sugar",
        "amount": 1,
        "unit": "tsp"
      },
      {
        "name": "Water",
        "amount": 2,
        "unit": "tsp"
      }
    ],
    "garnish": "Garnish with a mint sprig.",
    "method": "In a Julep cup, gently muddle the mint with sugar and water. Fill the glass with cracked ice, add the Bourbon and stir well until the cup frosts.",
    "note": null,
    "source": "Contemporary Classics"
  },
  {
    "name": "Mojito",
    "ingredients": [
      {
        "name": "White Rum",
        "amount": 45,
        "unit": "ml"
      },
      {
        "name": "Lime Juice",
        "amount": 20,
        "unit": "ml"
      },
      {
        "name": "Mint",
        "amount": 6,
        "unit": "sprigs"
      },
      {
        "name": "Sugar",
        "amount": 2,
        "unit": "tsp"
      },
      {
        "name": "Soda Water",
        "amount": null,
        "unit": "to top"
      }
    ],
    "garnish": "Garnish with sprigs of mint and slice of lime.",
    "method": "Mix mint springs with sugar and lime juice. Add splash of soda water and fill the glass with ice. Pour the rum and top with soda water. Light stir to involve all ingredients.",
    "note": null,
    "source": "Contemporary Classics"
  },
  {
    "name": "Moscow Mule",
    "ingredients": [
      {
        "name": "Vodka",
        "amount": 45,
        "unit": "ml"
      },
      {
        "name": "Ginger Beer",
        "amount": 120,
        "unit": "ml"
      },
      {
        "name": "Lime Juice",
        "amount": 10,
        "unit": "ml"
      }
    ],
    "garnish": "Garnish with a lime slice",
    "method": "In an Mule Cup or rocks glass, combine the vodka and ginger beer. Add lime juice and gently stir to involve all ingredients.",
    "note": null,
    "source": "Contemporary Classics"
  },
  {
    "name": "Pina Colada",
    "ingredients": [
      {
        "name": "White Rum",
        "amount": 50,
        "unit": "ml"
      },
      {
        "name": "Coconut Cream",
        "amount": 30,
        "unit": "ml"
      },
      {
        "name": "Pineapple Juice",
        "amount": 50,
        "unit": "ml"
      }
    ],
    "garnish": "Garnish with a slice of pineapple with a cocktail cherry.",
    "method": "Blend all the ingredients with ice in a electric blender, pour into a large glass and serve with straws.",
    "note": "Historically a few drops of fresh lime juice was added to taste. 4 slices of fresh pineapple can be used instead of juice.",
    "source": "Contemporary Classics"
  },
  {
    "name": "Pisco Sour",
    "ingredients": [
      {
        "name": "Pisco",
        "amount": 60,
        "unit": "ml"
      },
      {
        "name": "Lemon Juice",
        "amount": 30,
        "unit": "ml"
      },
      {
        "name": "Simple Syrup",
        "amount": 20,
        "unit": "ml"
      },
      {
        "name": "Egg White",
        "amount": 1,
        "unit": "egg"
      }
    ],
    "garnish": "Few dashes of Amargo bitters on top as an aromatic garnish.",
    "method": "Add all ingredients into a shaker with ice.\nShake and strain into a chilled goblet glass.",
    "note": null,
    "source": "Contemporary Classics"
  },
  {
    "name": "Sea Breeze",
    "ingredients": [
      {
        "name": "Vodka",
        "amount": 40,
        "unit": "ml"
      },
      {
        "name": "Cranberry Juice",
        "amount": 120,
        "unit": "ml"
      },
      {
        "name": "Grapefruit Juice",
        "amount": 30,
        "unit": "ml"
      }
    ],
    "garnish": "Garnish with an orange zest and cherry.",
    "method": "Build all ingredients in a highball glass filled with ice.",
    "note": null,
    "source": "Contemporary Classics"
  },
  {
    "name": "Sex on the Beach",
    "ingredients": [
      {
        "name": "Vodka",
        "amount": 40,
        "unit": "ml"
      },
      {
        "name": "Peach Liqueur",
        "amount": 20,
        "unit": "ml"
      },
      {
        "name": "Orange Juice",
        "amount": 40,
        "unit": "ml"
      },
      {
        "name": "Cranberry Juice",
        "amount": 40,
        "unit": "ml"
      }
    ],
    "garnish": "Garnish with half orange slice.",
    "method": "Build all ingredients in a highball glass filled with ice.",
    "note": null,
    "source": "Contemporary Classics"
  },
  {
    "name": "Singapore Sling",
    "ingredients": [
      {
        "name": "Gin",
        "amount": 30,
        "unit": "ml"
      },
      {
        "name": "Cherry Liqueur",
        "amount": 15,
        "unit": "ml"
      },
      {
        "name": "Cointreau",
        "amount": 7.5,
        "unit": "ml"
      },
      {
        "name": "Benedictine",
        "amount": 7.5,
        "unit": "ml"
      },
      {
        "name": "Pineapple Juice",
        "amount": 120,
        "unit": "ml"
      },
      {
        "name": "Lime Juice",
        "amount": 15,
        "unit": "ml"
      },
      {
        "name": "Grenadine",
        "amount": 10,
        "unit": "ml"
      },
      {
        "name": "Angostura Bitters",
        "amount": 1,
        "unit": "dash"
      }
    ],
    "garnish": "Garnish with pineapple and maraschino cherry",
    "method": "Pour all ingredients into cocktail shaker filled with ice cubes. Shake well. Strain into Hurricane glass.",
    "note": null,
    "source": "Contemporary Classics"
  },
  {
    "name": "Tequila Sunrise",
    "ingredients": [
      {
        "name": "Tequila Blanco",
        "amount": 45,
        "unit": "ml"
      },
      {
        "name": "Orange Juice",
        "amount": 90,
        "unit": "ml"
      },
      {
        "name": "Grenadine",
        "amount": 15,
        "unit": "ml"
      }
    ],
    "garnish": "Garnish with half orange slice or an orange zest",
    "method": "Pour tequila and orange juice directly into highball glass filled with ice cubes. Add the grenadine syrup to create chromatic effect (sunrise), do not stir.",
    "note": null,
    "source": "Contemporary Classics"
  },
  {
    "name": "Vesper",
    "ingredients": [
      {
        "name": "Gin",
        "amount": 45,
        "unit": "ml"
      },
      {
        "name": "Vodka",
        "amount": 15,
        "unit": "ml"
      },
      {
        "name": "Lillet Blanc",
        "amount": 7.5,
        "unit": "ml"
      }
    ],
    "garnish": "Garnish with lemon zest.",
    "method": "Pour all ingredients into cocktail shaker filled with ice cubes. Shake and strain into a chilled cocktail glass.",
    "note": null,
    "source": "Contemporary Classics"
  },
  {
    "name": "Zombie",
    "ingredients": [
      {
        "name": "Dark Jamaican Rum",
        "amount": 45,
        "unit": "ml"
      },
      {
        "name": "Gold Rum",
        "amount": 45,
        "unit": "ml"
      },
      {
        "name": "Demerara Rum",
        "amount": 30,
        "unit": "ml"
      },
      {
        "name": "Lime Juice",
        "amount": 20,
        "unit": "ml"
      },
      {
        "name": "Falernum",
        "amount": 15,
        "unit": "ml"
      },
      {
        "name": "Donn's Mix",
        "amount": 15,
        "unit": "ml"
      },
      {
        "name": "Grenadine",
        "amount": 1,
        "unit": "tsp"
      },
      {
        "name": "Angostura Bitters",
        "amount": 1,
        "unit": "dash"
      },
      {
        "name": "Pernod",
        "amount": 6,
        "unit": "drops"
      }
    ],
    "garnish": "Garnish with mint leaves.",
    "method": "Add all ingredients into an electric blender with 170 grams of cracked ice. With pulse bottom blend for a few seconds. Serve in a tall tumbler glass.",
    "note": "Donn’s Mix: 2 parts of fresh yellow grapefruit and 1 part of cinnamon syrup",
    "source": "Contemporary Classics"
  },
  {
    "name": "Barracuda",
    "ingredients": [
      {
        "name": "Gold Rum",
        "amount": 45,
        "unit": "ml"
      },
      {
        "name": "Galliano",
        "amount": 15,
        "unit": "ml"
      },
      {
        "name": "Pineapple Juice",
        "amount": 60,
        "unit": "ml"
      },
      {
        "name": "Lime Juice",
        "amount": 60,
        "unit": "ml"
      },
      {
        "name": "Prosecco",
        "amount": null,
        "unit": "to top"
      }
    ],
    "garnish": "Pineapple and Cherry, optional mint spring for additional aroma.",
    "method": "Pour all ingredients into cocktail shaker except the Prosecco, shake well with ice, strain into chilled highball glass filled with ice and top up with Prosecco.",
    "note": null,
    "source": "New Era Drinks"
  },
  {
    "name": "Bee's Knees",
    "ingredients": [
      {
        "name": "Dry gin",
        "amount": 52.5,
        "unit": "ml"
      },
      {
        "name": "Honey Syrup",
        "amount": 2,
        "unit": "tsp"
      },
      {
        "name": "Lemon Juice",
        "amount": 22.5,
        "unit": "ml"
      },
      {
        "name": "Orange Juice",
        "amount": 22.5,
        "unit": "ml"
      }
    ],
    "garnish": "Optionally garnish with a lemon or orange zest.",
    "method": "Stir honey with lemon and orange juices until it dissolves, add gin and shake with ice. Strain into a chilled cocktail glass.",
    "note": null,
    "source": "New Era Drinks"
  },
  {
    "name": "Bramble",
    "ingredients": [
      {
        "name": "Gin",
        "amount": 50,
        "unit": "ml"
      },
      {
        "name": "Lemon Juice",
        "amount": 20,
        "unit": "ml"
      },
      {
        "name": "Simple Syrup",
        "amount": 12.5,
        "unit": "ml"
      },
      {
        "name": "Creme de Mure",
        "amount": 15,
        "unit": "ml"
      }
    ],
    "garnish": "Garnish optionally with a lemon slice and blackberries.",
    "method": "Pour all ingredients into cocktail shaker except the Creme de Mure, shake well with ice, strain into chilled old fashioned glass filled with crushed ice, then pour the blackberry liqueur (Creme de Mure) over the top of the drink, in a circular motion.",
    "note": null,
    "source": "New Era Drinks"
  },
  {
    "name": "Canchanchara",
    "ingredients": [
      {
        "name": "Cuban Aquardiente",
        "amount": 60,
        "unit": "ml"
      },
      {
        "name": "Lime Juice",
        "amount": 15,
        "unit": "ml"
      },
      {
        "name": "Honey",
        "amount": 15,
        "unit": "ml"
      },
      {
        "name": "Water",
        "amount": 50,
        "unit": "ml"
      }
    ],
    "garnish": "Garnish with a lime wedge.",
    "method": "Mix honey with water and lime juice and spread the mixture on the bottom and sides of the glass. Add cracked ice, and then the rum. End by energetically stirring from bottom to top.",
    "note": null,
    "source": "New Era Drinks"
  },
  {
    "name": "Dark 'n Stormy",
    "ingredients": [
      {
        "name": "Black Rum",
        "amount": 60,
        "unit": "ml"
      },
      {
        "name": "Ginger Beer",
        "amount": 100,
        "unit": "ml"
      }
    ],
    "garnish": "Garnish with a lime wedge or slice.",
    "method": "In a highball glass  filled with ice pour the ginger beer and top floating with the Rum.",
    "note": "Officially this cocktail is done with Gosling's Black Seal Rum",
    "source": "New Era Drinks"
  },
  {
    "name": "Espresso Martini",
    "ingredients": [
      {
        "name": "Vodka",
        "amount": 50,
        "unit": "ml"
      },
      {
        "name": "Coffee Liqueur",
        "amount": 30,
        "unit": "ml"
      },
      {
        "name": "Simple Syrup",
        "amount": 10,
        "unit": "ml"
      },
      {
        "name": "Espresso",
        "amount": 30,
        "unit": "ml"
      }
    ],
    "garnish": null,
    "method": "Pour all ingredients into cocktail shaker, shake well with ice, strain into chilled cocktail glass.",
    "note": null,
    "source": "New Era Drinks"
  },
  {
    "name": "Fernandito",
    "ingredients": [
      {
        "name": "Fernet Branca",
        "amount": 50,
        "unit": "ml"
      },
      {
        "name": "Cola",
        "amount": null,
        "unit": "to top"
      }
    ],
    "garnish": null,
    "method": "Pour the Fernet Branca into a double old fashioned glass with ice, fill the glass up with Cola. Gently stir.",
    "note": null,
    "source": "New Era Drinks"
  },
  {
    "name": "French Martini",
    "ingredients": [
      {
        "name": "Vodka",
        "amount": 45,
        "unit": "ml"
      },
      {
        "name": "Raspberry Liqueur",
        "amount": 15,
        "unit": "ml"
      },
      {
        "name": "Pineapple Juice",
        "amount": 15,
        "unit": "ml"
      }
    ],
    "garnish": "Squeeze oil from lemon peel onto the drink.",
    "method": "Pour all ingredients into cocktail shaker, shake well with ice, strain into chilled cocktail glass.",
    "note": null,
    "source": "New Era Drinks"
  },
  {
    "name": "Illegal",
    "ingredients": [
      {
        "name": "Espadin Mezcal",
        "amount": 30,
        "unit": "ml"
      },
      {
        "name": "Light Overproof Jamaican Rum",
        "amount": 15,
        "unit": "ml"
      },
      {
        "name": "Falernum",
        "amount": 15,
        "unit": "ml"
      },
      {
        "name": "Maraschino Liqueur",
        "amount": 1,
        "unit": "barspoon"
      },
      {
        "name": "Lime Juice",
        "amount": 22.5,
        "unit": "ml"
      },
      {
        "name": "Simple Syrup",
        "amount": 15,
        "unit": "ml"
      },
      {
        "name": "Egg white",
        "amount": null,
        "unit": "a few drops of"
      }
    ],
    "garnish": null,
    "method": "Pour all ingredients into the shaker. Shake vigorously with ice.  Strain into a chilled cocktail glass, or “on the rocks” in a traditional clay or terracotta mug.",
    "note": null,
    "source": "New Era Drinks"
  },
  {
    "name": "Lemon Drop Martini",
    "ingredients": [
      {
        "name": "Vodka Citron",
        "amount": 30,
        "unit": "ml"
      },
      {
        "name": "Triple Sec",
        "amount": 20,
        "unit": "ml"
      },
      {
        "name": "Lemon Juice",
        "amount": 15,
        "unit": "ml"
      }
    ],
    "garnish": "Garnish with sugar rim arround the glass.",
    "method": "Pour all ingredients into cocktail shaker, shake well with ice, strain into chilled cocktail glass.",
    "note": null,
    "source": "New Era Drinks"
  },
  {
    "name": "Naked and Famous",
    "ingredients": [
      {
        "name": "Mezcal",
        "amount": 22.5,
        "unit": "ml"
      },
      {
        "name": "Yellow Charteuse",
        "amount": 22.5,
        "unit": "ml"
      },
      {
        "name": "Aperol",
        "amount": 22.5,
        "unit": "ml"
      },
      {
        "name": "Lime juice",
        "amount": 22.5,
        "unit": "ml"
      }
    ],
    "garnish": null,
    "method": "Pour all ingredients into cocktail shaker, shake well with ice, strain into chilled cocktail glass.",
    "note": null,
    "source": "New Era Drinks"
  },
  {
    "name": "New York Sour",
    "ingredients": [
      {
        "name": "Rye Whiskey",
        "amount": 60,
        "unit": "ml"
      },
      {
        "name": "Simple Syrup",
        "amount": 22.5,
        "unit": "ml"
      },
      {
        "name": "Lemon Juice",
        "amount": 30,
        "unit": "ml"
      },
      {
        "name": "Red Wine",
        "amount": 15,
        "unit": "ml"
      },
      {
        "name": "Egg White",
        "amount": null,
        "unit": "a few drops of"
      }
    ],
    "garnish": "Garnish with lemon or orange zest with cherry.",
    "method": "Pour all ingredients into the shaker. Shake vigorously with ice.  Strain into a chilled rocks glass filled with ice. Float the wine on top.",
    "note": "Use Shiraz or Malbech wine",
    "source": "New Era Drinks"
  },
  {
    "name": "Old cuban",
    "ingredients": [
      {
        "name": "Mint",
        "amount": 7,
        "unit": "leaves"
      },
      {
        "name": "Aged Rum",
        "amount": 45,
        "unit": "ml"
      },
      {
        "name": "Lime Juice",
        "amount": 22.5,
        "unit": "ml"
      },
      {
        "name": "Simple Syrup",
        "amount": 30,
        "unit": "ml"
      },
      {
        "name": "Angostura Bitters",
        "amount": 2,
        "unit": "dashes"
      },
      {
        "name": "Champagne",
        "amount": 60,
        "unit": "ml"
      }
    ],
    "garnish": "Garnish with mint springs.",
    "method": "Pour all ingredients into cocktail shaker except the sparkling wine, shake well with ice, strain into chilled elegant cocktail glass. Top up with the sparkling wine.",
    "note": null,
    "source": "New Era Drinks"
  },
  {
    "name": "Paloma",
    "ingredients": [
      {
        "name": "Tequila Blanco",
        "amount": 50,
        "unit": "ml"
      },
      {
        "name": "Lime Juice",
        "amount": 5,
        "unit": "ml"
      },
      {
        "name": "Salt",
        "amount": 1,
        "unit": "pinch"
      },
      {
        "name": "Grapefruit Soda",
        "amount": 100,
        "unit": "ml"
      }
    ],
    "garnish": "Garnish with a slice of lime.",
    "method": "Poor the tequila into a highball glass, squeeze the lime juice. Add ice and salt, fill up pink grapefruit soda. Stir gently.",
    "note": null,
    "source": "New Era Drinks"
  },
  {
    "name": "Paper Plane",
    "ingredients": [
      {
        "name": "Bourbon",
        "amount": 30,
        "unit": "ml"
      },
      {
        "name": "Amaro Nonino",
        "amount": 30,
        "unit": "ml"
      },
      {
        "name": "Aperol",
        "amount": 30,
        "unit": "ml"
      },
      {
        "name": "Lemon Juice",
        "amount": 30,
        "unit": "ml"
      }
    ],
    "garnish": null,
    "method": "Pour all ingredients into cocktail shaker, shake well with ice, strain into chilled cocktail glass.",
    "note": null,
    "source": "New Era Drinks"
  },
  {
    "name": "Penicillin",
    "ingredients": [
      {
        "name": "Blended Scotch Whisky",
        "amount": 60,
        "unit": "ml"
      },
      {
        "name": "Peated Whisky",
        "amount": 7.5,
        "unit": "ml"
      },
      {
        "name": "Lemon Juice",
        "amount": 22.5,
        "unit": "ml"
      },
      {
        "name": "Honey Syrup",
        "amount": 22.5,
        "unit": "ml"
      },
      {
        "name": "Ginger",
        "amount": 3,
        "unit": "slices"
      }
    ],
    "garnish": "Garnish with a candied ginger.",
    "method": "Muddle fresh ginger in a shaker and add the remaining ingredients, except for the Islay single malt whiskey. Fill the shaker with ice and shake. Double-strain into a chilled old fashioned glass with ice. Float the single malt whisky on top.",
    "note": "The official notes suggest Lagavulin 16 years old whisky for the peated whisky.",
    "source": "New Era Drinks"
  },
  {
    "name": "Russian Spring Punch",
    "ingredients": [
      {
        "name": "Vodka",
        "amount": 25,
        "unit": "ml"
      },
      {
        "name": "Lemon Juice",
        "amount": 25,
        "unit": "ml"
      },
      {
        "name": "Creme de Cassis",
        "amount": 10,
        "unit": "ml"
      },
      {
        "name": "Simple Syrup",
        "amount": 10,
        "unit": "ml"
      },
      {
        "name": "Sparkling Wine",
        "amount": null,
        "unit": "to top"
      }
    ],
    "garnish": "Garnish with blackberries and optionally a lemon slice as well.",
    "method": "Pour all ingredients into cocktail shaker except the sparkling wine, shake well with ice, strain into chilled tall tumbler glass filled with ice and top up with sparkling wine.",
    "note": null,
    "source": "New Era Drinks"
  },
  {
    "name": "Southside",
    "ingredients": [
      {
        "name": "London Dry Gin",
        "amount": 60,
        "unit": "ml"
      },
      {
        "name": "Lemon Juice",
        "amount": 30,
        "unit": "ml"
      },
      {
        "name": "Simple Syrup",
        "amount": 15,
        "unit": "ml"
      },
      {
        "name": "Mint",
        "amount": 6,
        "unit": "leaves"
      },
      {
        "name": "Egg White",
        "amount": null,
        "unit": "a few drops of"
      }
    ],
    "garnish": "Garnish with mint springs.",
    "method": "Pour all ingredients into a cocktail shaker, shake well with ice, double-strain into chilled cocktail glass.\nIf egg white is used shake vigorously.",
    "note": null,
    "source": "New Era Drinks"
  },
  {
    "name": "Spicy Fifty",
    "ingredients": [
      {
        "name": "Vanilla Vodka",
        "amount": 50,
        "unit": "ml"
      },
      {
        "name": "Elderflower Cordial",
        "amount": 15,
        "unit": "ml"
      },
      {
        "name": "Lemon Juice",
        "amount": 15,
        "unit": "ml"
      },
      {
        "name": "Honey Syrup",
        "amount": 10,
        "unit": "ml"
      },
      {
        "name": "Red Chili Pepper",
        "amount": 2,
        "unit": "slices"
      }
    ],
    "garnish": "Garnish with a red chili pepper",
    "method": "Pour all ingredients into a cocktail shaker, shake well with ice, double-strain into chilled cocktail glass.",
    "note": "The official notes specify the honey syrup from Monin.",
    "source": "New Era Drinks"
  },
  {
    "name": "Aperol Spritz",
    "ingredients": [
      {
        "name": "Prosecco",
        "amount": 90,
        "unit": "ml"
      },
      {
        "name": "Aperol",
        "amount": 60,
        "unit": "ml"
      },
      {
        "name": "Soda Water",
        "amount": 1,
        "unit": "splash"
      }
    ],
    "garnish": "Garnish with a slice of orange.",
    "method": "Build all ingredients into a wine glass filled with ice. Stir gently.",
    "note": "There are other versions of the Spritz that use Campari, Cynar or Select instead of Aperol.",
    "source": "New Era Drinks"
  },
  {
    "name": "Suffering Bastard",
    "ingredients": [
      {
        "name": "Cognac",
        "amount": 30,
        "unit": "ml"
      },
      {
        "name": "Gin",
        "amount": 30,
        "unit": "ml"
      },
      {
        "name": "Lime Juice",
        "amount": 15,
        "unit": "ml"
      },
      {
        "name": "Angostura Bitters",
        "amount": 2,
        "unit": "dashes"
      },
      {
        "name": "Ginger Beer",
        "amount": null,
        "unit": "to top"
      }
    ],
    "garnish": "Garnish with mint spring and optionally an orange slice as well.",
    "method": "Pour all ingredients into cocktail shaker except the ginger beer, shake well with ice, Pour unstrained into a Collins glass or in the original Suffering Bastard mug and top up with ginger beer.",
    "note": null,
    "source": "New Era Drinks"
  },
  {
    "name": "Tipperary",
    "ingredients": [
      {
        "name": "Irish Whiskey",
        "amount": 50,
        "unit": "ml"
      },
      {
        "name": "Sweet Vermouth",
        "amount": 25,
        "unit": "ml"
      },
      {
        "name": "Green Chartreuse",
        "amount": 15,
        "unit": "ml"
      },
      {
        "name": "Angostura Bitters",
        "amount": 2,
        "unit": "dashes"
      }
    ],
    "garnish": "Garnish with a slice of orange.",
    "method": "Pour all ingredients into mixing glass with ice cubes. Stir well. Strain into chilled martini cocktail glass.",
    "note": null,
    "source": "New Era Drinks"
  },
  {
    "name": "Tommy's Margarita",
    "ingredients": [
      {
        "name": "Tequila Reposado",
        "amount": 60,
        "unit": "ml"
      },
      {
        "name": "Lime Juice",
        "amount": 30,
        "unit": "ml"
      },
      {
        "name": "Agave Syrup",
        "amount": 30,
        "unit": "ml"
      }
    ],
    "garnish": "Garnish with a lime slice.",
    "method": "Pour all ingredients into a cocktail shaker, shake well with ice, strain into chilled rocks glass filled with ice.",
    "note": null,
    "source": "New Era Drinks"
  },
  {
    "name": "Trinidad Sour",
    "ingredients": [
      {
        "name": "Angostura Bitters",
        "amount": 45,
        "unit": "ml"
      },
      {
        "name": "Orgeat Syrup",
        "amount": 30,
        "unit": "ml"
      },
      {
        "name": "Lemon Juice",
        "amount": 22.5,
        "unit": "ml"
      },
      {
        "name": "Rye Whiskey",
        "amount": 15,
        "unit": "ml"
      }
    ],
    "garnish": null,
    "method": "Pour all ingredients into cocktail shaker, shake well with ice, strain into chilled cocktail glass.",
    "note": null,
    "source": "New Era Drinks"
  },
  {
    "name": "VE.N.TO",
    "ingredients": [
      {
        "name": "White Grappa",
        "amount": 45,
        "unit": "ml"
      },
      {
        "name": "Lemon Juice",
        "amount": 2.5,
        "unit": "ml"
      },
      {
        "name": "Honey syrup",
        "amount": 15,
        "unit": "ml"
      },
      {
        "name": "Chamomille Cordial",
        "amount": 15,
        "unit": "ml"
      },
      {
        "name": "Egg white",
        "amount": 10,
        "unit": "ml"
      }
    ],
    "garnish": "Garnish with lemon zest and white grapes.",
    "method": "Pour all ingredients into the shaker. Shake vigorously with ice. Strain into a chilled small tumbler glass filled with ice.",
    "note": null,
    "source": "New Era Drinks"
  },
  {
    "name": "Yellow Bird",
    "ingredients": [
      {
        "name": "White Rum",
        "amount": 30,
        "unit": "ml"
      },
      {
        "name": "Galliano",
        "amount": 15,
        "unit": "ml"
      },
      {
        "name": "Triple Sec",
        "amount": 15,
        "unit": "ml"
      },
      {
        "name": "Lime Juice",
        "amount": 15,
        "unit": "ml"
      }
    ],
    "garnish": null,
    "method": "Pour all ingredients into a cocktail shaker, shake well with ice, strain into chilled cocktail glass.",
    "note": null,
    "source": "New Era Drinks"
  }
]
